[
	null,
	{"id":1,"expanded":true,"name":"MAP001_心理測驗and前導劇情","order":2,"parentId":0,"scrollX":557.3333333333334,"scrollY":565.7777777777778},
	{"id":2,"expanded":true,"name":"MAP002_勇者房間2F","order":4,"parentId":5,"scrollX":557.3333333333334,"scrollY":565.7777777777778},
	{"id":3,"expanded":true,"name":"MAP_003_勇者回憶01","order":5,"parentId":5,"scrollX":968.8888888888889,"scrollY":864.4444444444445},
	{"id":4,"expanded":false,"name":"MAP_004_勇者回憶02","order":6,"parentId":5,"scrollX":986,"scrollY":628.5},
	{"id":5,"expanded":true,"name":"MAP002_勇者房間1F","order":3,"parentId":1,"scrollX":619,"scrollY":636.5},
	{"id":6,"expanded":false,"name":"MAP_006_王國比武場","order":7,"parentId":5,"scrollX":861,"scrollY":628.5},
	{"id":7,"expanded":false,"name":"MAP_007世界地圖","order":8,"parentId":5,"scrollX":2119.2,"scrollY":3259.7999999999997},
	{"id":8,"expanded":true,"name":"MAP008_魔王城","order":9,"parentId":0,"scrollX":742.8,"scrollY":1165.8},
	{"id":9,"expanded":false,"name":"MAP009_魔王房間","order":10,"parentId":8,"scrollX":752.4,"scrollY":763.8},
	{"id":10,"expanded":true,"name":"MAP010＿食堂/煉金室_劇情用","order":20,"parentId":20,"scrollX":752.4,"scrollY":763.8},
	{"id":11,"expanded":false,"name":"MAP011_會議室","order":21,"parentId":8,"scrollX":752.4,"scrollY":763.8},
	{"id":12,"expanded":false,"name":"MAP012＿寵物屋","order":11,"parentId":8,"scrollX":627,"scrollY":636.5},
	{"id":13,"expanded":false,"name":"MAP013_女主角臥室走廊","order":12,"parentId":8,"scrollX":752.4,"scrollY":763.8},
	{"id":14,"expanded":false,"name":"MAP014_圖書館","order":13,"parentId":8,"scrollX":752.4,"scrollY":763.8},
	{"id":15,"expanded":false,"name":"MAP015_傳送陣","order":14,"parentId":8,"scrollX":627,"scrollY":636.5},
	{"id":16,"expanded":false,"name":"MAP016_抽卡介面","order":22,"parentId":0,"scrollX":1504.8,"scrollY":1306.8},
	{"id":17,"expanded":false,"name":"MAP017＿練武場_新手訓練","order":17,"parentId":21,"scrollX":675.2727272727273,"scrollY":889.6363636363636},
	{"id":18,"expanded":true,"name":"MAP018＿地牢","order":15,"parentId":8,"scrollX":688,"scrollY":767.5},
	{"id":19,"expanded":true,"name":"MAP019＿農田(LV1)","order":18,"parentId":8,"scrollX":752.4,"scrollY":763.8},
	{"id":20,"expanded":true,"name":"MAP020＿食堂/煉金室","order":19,"parentId":8,"scrollX":627,"scrollY":636.5},
	{"id":21,"expanded":true,"name":"MAP021＿練武場","order":16,"parentId":8,"scrollX":619,"scrollY":767.5},
	{"id":22,"expanded":false,"name":"MAP022_測試地圖","order":1,"parentId":0,"scrollX":684,"scrollY":594},
	{"id":23,"expanded":true,"name":"MAP023_泡泡球群島","order":23,"parentId":0,"scrollX":675.2727272727273,"scrollY":1086},
	{"id":24,"expanded":true,"name":"MAP024_泡泡球群島(2)","order":24,"parentId":23,"scrollX":675.2727272727273,"scrollY":1823.4545454545455},
	{"id":25,"expanded":false,"name":"MAP025_泡泡球群島(3)","order":25,"parentId":23,"scrollX":1485.6,"scrollY":1287.6}
]